pyramid_fanstatic/__init__.py
pyramid_fanstatic/scaffolds.py
pyramid_fanstatic/tests.py
pyramid_fanstatic/scaffold/README_FANSTATIC.txt_tmpl
pyramid_fanstatic/scaffold/+package+/resources.py_tmpl
pyramid_fanstatic/scaffold/+package+/resources/main.css_tmpl
pyramid_fanstatic/scaffold/+package+/resources/main.js_tmpl
pyramid_fanstatic/scaffold/+package+/resources/main.less_tmpl
pyramid_fanstatic-0.6.dist-info/METADATA
pyramid_fanstatic-0.6.dist-info/WHEEL
pyramid_fanstatic-0.6.dist-info/entry_points.txt
pyramid_fanstatic-0.6.dist-info/top_level.txt
pyramid_fanstatic-0.6.dist-info/RECORD
