Metadata-Version: 2.1
Name: pyramid-fanstatic
Version: 0.6
Summary: pyramid tween for fanstatic
Home-page: https://github.com/FormAlchemy/pyramid_fanstatic
Author: Gael Pasgrimaud
Author-email: gael@gawel.org
License: MIT
Keywords: pyramid fanstatic js css
Platform: UNKNOWN
Classifier: Intended Audience :: Developers
Classifier: Programming Language :: Python
Classifier: Programming Language :: Python :: 2
Classifier: Programming Language :: Python :: 2.7
Classifier: Programming Language :: Python :: 3
Classifier: Programming Language :: Python :: 3.7
Classifier: Programming Language :: Python :: 3.8
Classifier: Framework :: Pylons
Classifier: Topic :: Internet :: WWW/HTTP :: WSGI
Classifier: License :: OSI Approved :: MIT License
Requires-Dist: pyramid
Requires-Dist: fanstatic
Provides-Extra: test
Requires-Dist: js.jquery (==1.9.1) ; extra == 'test'
Requires-Dist: webtest ; extra == 'test'
